{
  "id": "lesson_9",
  "title": "日常用语 — Повседневные фразы: живой язык",
  "level": "hsk0",
  "language": "chinese",
  "xpReward": 40,
  "estimatedMinutes": 30,
  "intro": {
    "text": "Перед тем как перейти на HSK 1 — давай выучим живые повседневные фразы. Не только учебные, но и те что реально используются в Китае каждый день. После этого ты будешь звучать естественно, а не по-учебнику.",
    "goals": [
      "Выучить 12 повседневных фраз",
      "Понять разницу учебного и живого китайского",
      "Использовать 语气词 (частицы настроения)",
      "Вести простой диалог"
    ]
  },
  "grammar": [
    {
      "id": "g1",
      "title": "Частицы настроения 语气词 — душа китайского",
      "explanation": "Китайский язык полон маленькими частицами в конце предложений которые передают настроение, вопрос, эмоцию. Без них речь звучит сухо и механически.",
      "table": {
        "headers": [
          "Частица",
          "Значение",
          "Пример",
          "Эмоция"
        ],
        "rows": [
          [
            "吧 ba",
            "предложение/предположение",
            "Wǒmen qù ba! — Пойдём!",
            "Призыв, согласование"
          ],
          [
            "啊 a",
            "восклицание/смягчение",
            "Hǎo a! — Хорошо!",
            "Радость, смягчение"
          ],
          [
            "嘛 ma",
            "очевидность",
            "Tā shì nǚrén ma. — Ну она же женщина.",
            "Само собой разумеется"
          ],
          [
            "呢 ne",
            "вопрос-возврат",
            "Nǐ ne? — А ты?",
            "Возвращение вопроса"
          ],
          [
            "了 le",
            "изменение состояния",
            "Wǒ dǒng le. — Я понял.",
            "Произошло изменение"
          ],
          [
            "哦 ō",
            "понимание",
            "Ō, yuánlái rúcǐ. — О, вот оно как.",
            "Понял что-то новое"
          ]
        ]
      },
      "note": "吧 (ba) — очень многофункциональная частица. Nǐ shì xuésheng ba? = Ты ведь студент? (предположение). Wǒmen zǒu ba! = Пошли! (призыв)."
    }
  ],
  "vocabulary": [
    {
      "tr": "哈哈 hāhā",
      "ru": "хаха (смех)",
      "pronunciation": "ха-ха",
      "example_tr": "哈哈，太好笑了！",
      "example_ru": "Хахаха, так смешно!"
    },
    {
      "tr": "哇 wā",
      "ru": "вау! (восхищение)",
      "pronunciation": "ва",
      "example_tr": "哇！真漂亮！",
      "example_ru": "Вау! Как красиво!"
    },
    {
      "tr": "唉 āi",
      "ru": "ах/эх (вздох)",
      "pronunciation": "ай",
      "example_tr": "唉，没办法。",
      "example_ru": "Эх, ничего не поделаешь."
    },
    {
      "tr": "加油 jiāyóu",
      "ru": "давай! не сдавайся!",
      "pronunciation": "цзя-ю",
      "example_tr": "加油！你能行！",
      "example_ru": "Давай! Ты сможешь!"
    },
    {
      "tr": "没事 méishì",
      "ru": "всё нормально",
      "pronunciation": "мэй-ши",
      "example_tr": "没事，不要担心。",
      "example_ru": "Всё нормально, не беспокойся."
    },
    {
      "tr": "随便 suíbiàn",
      "ru": "как хочешь/всё равно",
      "pronunciation": "суй-бянь",
      "example_tr": "随便，都可以。",
      "example_ru": "Как хочешь, всё возможно."
    },
    {
      "tr": "差不多 chàbuduō",
      "ru": "примерно/приблизительно",
      "pronunciation": "ча-бу-дуо",
      "example_tr": "差不多了。",
      "example_ru": "Почти готово."
    },
    {
      "tr": "没问题 méi wèntí",
      "ru": "нет проблем",
      "pronunciation": "мэй-вэнь-ти",
      "example_tr": "没问题，包在我身上！",
      "example_ru": "Нет проблем, беру на себя!"
    },
    {
      "tr": "慢慢来 mànmàn lái",
      "ru": "не спеши",
      "pronunciation": "мань-мань-лай",
      "example_tr": "慢慢来，不着急。",
      "example_ru": "Не спеши, не к спеху."
    },
    {
      "tr": "再说吧 zài shuō ba",
      "ru": "поговорим позже",
      "pronunciation": "цзай-шуо-ба",
      "example_tr": "再说吧，现在忙。",
      "example_ru": "Поговорим позже, сейчас занят."
    },
    {
      "tr": "辛苦了 xīnkǔ le",
      "ru": "спасибо за труды",
      "pronunciation": "синь-ку-лэ",
      "example_tr": "辛苦了！您辛苦了！",
      "example_ru": "Спасибо за труды!"
    },
    {
      "tr": "保重 bǎozhòng",
      "ru": "береги себя",
      "pronunciation": "бао-чжун",
      "example_tr": "保重！一路平安！",
      "example_ru": "Береги себя! Счастливого пути!"
    }
  ],
  "dialogue": {
    "title": "Практика урока 9",
    "context": "Тренируем произношение.",
    "lines": [
      {
        "speaker": "Ань",
        "tr": "Lǎoshī，wǒ dǒng le！",
        "ru": "Учитель, я понял!",
        "note": "了 le = изменение состояния (теперь понимаю)"
      },
      {
        "speaker": "Учитель",
        "tr": "Hǎo a! Màn màn lái, bié zháo jí.",
        "ru": "Отлично! Не спеши, не торопись.",
        "note": "bié = не (запрет), zháo jí = торопиться"
      },
      {
        "speaker": "Ань",
        "tr": "Jiāyóu! Wǒ yīdìng néng xué hǎo!",
        "ru": "Давай! Я обязательно смогу выучить!",
        "note": "yīdìng = обязательно, néng = мочь"
      }
    ]
  },
  "cultural_note": {
    "title": "加油 — национальный призыв",
    "text": "加油 jiāyóu буквально = 'добавь масла/топлива'. Это универсальный возглас поддержки: болельщики кричат спортсменам, родители детям перед экзаменом, друзья другу в трудную минуту. На Олимпиаде китайские болельщики скандируют: 中国加油！(Zhōngguó jiāyóu = Китай, давай!). Это слово ты услышишь в Китае повсюду."
  },
  "exercises": [
    {
      "id": "ex_1",
      "type": "multiple_choice",
      "question": "吧 (ba) в конце предложения передаёт...",
      "options": [
        "вопрос да/нет",
        "предположение или призыв",
        "прошедшее время",
        "отрицание"
      ],
      "correctAnswer": "предположение или призыв",
      "explanation": "吧 = призыв (Wǒmen qù ba! = Пойдём!) или предположение (Nǐ shì xuésheng ba? = Ты ведь студент?)."
    },
    {
      "id": "ex_2",
      "type": "multiple_choice",
      "question": "加油 jiāyóu означает...",
      "options": [
        "добавь воды",
        "заправь машину",
        "давай/не сдавайся",
        "хватит есть"
      ],
      "correctAnswer": "давай/не сдавайся",
      "explanation": "加油 = давай/не сдавайся (буквально: добавь масла). Универсальный призыв к действию!"
    },
    {
      "id": "ex_3",
      "type": "match_pairs",
      "question": "Соедини частицы",
      "pairs": [
        {
          "left": "吧",
          "right": "предложение"
        },
        {
          "left": "呢",
          "right": "вопрос-возврат"
        },
        {
          "left": "了",
          "right": "изменение состояния"
        },
        {
          "left": "啊",
          "right": "восклицание"
        }
      ],
      "correctAnswer": "all",
      "explanation": "吧=предложение/призыв, 呢=а ты?/вопрос, 了=изменение, 啊=восклицание."
    },
    {
      "id": "ex_4",
      "type": "multiple_choice",
      "question": "'Нет проблем' по-китайски:",
      "options": [
        "没事",
        "没问题",
        "没关系",
        "没了"
      ],
      "correctAnswer": "没问题",
      "explanation": "没问题 méi wèntí = нет проблем. 没事 = ничего/всё нормально. 没关系 = ничего страшного."
    },
    {
      "id": "ex_5",
      "type": "fill_blank",
      "question": "'Береги себя' = '___！'",
      "options": [
        "加油",
        "随便",
        "保重",
        "差不多"
      ],
      "correctAnswer": "保重",
      "explanation": "保重 bǎozhòng = береги себя. Говорят при расставании надолго. 保 = сохранять, 重 = важный/тяжёлый."
    },
    {
      "id": "ex_6",
      "type": "multiple_choice",
      "question": "'Wǒ dǒng le' означает:",
      "options": [
        "Я понял",
        "Я не понял",
        "Я знаю",
        "Я хочу"
      ],
      "correctAnswer": "Я понял",
      "explanation": "dǒng = понимать. 了 le = изменение состояния (произошло понимание). Wǒ dǒng le = Я понял!"
    },
    {
      "id": "ex_7",
      "type": "multiple_choice",
      "question": "'Не спеши' по-китайски:",
      "options": [
        "快点",
        "慢慢来",
        "加油",
        "再说吧"
      ],
      "correctAnswer": "慢慢来",
      "explanation": "慢慢来 mànmàn lái = не спеши (буквально: медленно-медленно иди). 慢 = медленный."
    },
    {
      "id": "ex_8",
      "type": "fill_blank",
      "question": "'Как хочешь' = '___'",
      "options": [
        "加油",
        "没事",
        "随便",
        "保重"
      ],
      "correctAnswer": "随便",
      "explanation": "随便 suíbiàn = как хочешь/всё равно. 随 = следовать, 便 = удобно. Очень частый ответ когда нет предпочтений."
    }
  ],
  "summary": {
    "title": "Что ты выучил",
    "points": [
      "日常用语 — Повседневные фразы: живой язык"
    ],
    "next_lesson": "Урок 10"
  }
}