{
  "id": "lesson_11",
  "title": "第一批汉字 — Первые 10 иероглифов",
  "level": "hsk0",
  "language": "chinese",
  "xpReward": 40,
  "estimatedMinutes": 25,
  "intro": {
    "text": "Начинаем писать иероглифы! Первые 10: 一 (один), 二 (два), 三 (три), 人 (человек), 口 (рот), 日 (солнце), 月 (луна), 山 (гора), 水 (вода), 火 (огонь). Все они пиктографические — напоминают то что обозначают.",
    "goals": [
      "Писать первые 10 иероглифов",
      "Запомнить порядок черт",
      "Понять пиктографический смысл",
      "Читать их в пиньине"
    ]
  },
  "grammar": [
    {
      "id": "g1",
      "title": "Первые 10 иероглифов",
      "explanation": "Начинаем писать иероглифы! Первые 10: 一 (один), 二 (два), 三 (три), 人 (человек), 口 (рот), 日 (солнце), 月 (луна), 山 (гора), 水 (вода), 火 (огонь). Все они пиктографические — напоминают то что обозначают.",
      "table": {
        "headers": [
          "Иероглиф/Правило",
          "Пиньинь",
          "Значение/Описание"
        ],
        "rows": [
          [
            "一 yī",
            "один (1 черта)",
            "[и]"
          ],
          [
            "二 èr",
            "два (2 черты)",
            "[эр]"
          ],
          [
            "三 sān",
            "три (3 черты)",
            "[сань]"
          ],
          [
            "人 rén",
            "человек",
            "[жэнь]"
          ],
          [
            "口 kǒu",
            "рот",
            "[коу]"
          ]
        ]
      },
      "note": "💡 Писать первые 10 иероглифов"
    }
  ],
  "vocabulary": [
    {
      "tr": "一 yī",
      "ru": "один (1 черта)",
      "pronunciation": "[и]",
      "example_tr": "一个",
      "example_ru": "один"
    },
    {
      "tr": "二 èr",
      "ru": "два (2 черты)",
      "pronunciation": "[эр]",
      "example_tr": "二月",
      "example_ru": "февраль"
    },
    {
      "tr": "三 sān",
      "ru": "три (3 черты)",
      "pronunciation": "[сань]",
      "example_tr": "三点",
      "example_ru": "три часа"
    },
    {
      "tr": "人 rén",
      "ru": "человек",
      "pronunciation": "[жэнь]",
      "example_tr": "一个人",
      "example_ru": "один человек"
    },
    {
      "tr": "口 kǒu",
      "ru": "рот",
      "pronunciation": "[коу]",
      "example_tr": "开口",
      "example_ru": "открой рот"
    },
    {
      "tr": "日 rì",
      "ru": "солнце",
      "pronunciation": "[жы]",
      "example_tr": "今日",
      "example_ru": "сегодня"
    },
    {
      "tr": "月 yuè",
      "ru": "луна",
      "pronunciation": "[юэ]",
      "example_tr": "月亮",
      "example_ru": "луна"
    },
    {
      "tr": "山 shān",
      "ru": "гора",
      "pronunciation": "[шань]",
      "example_tr": "大山",
      "example_ru": "большая гора"
    },
    {
      "tr": "水 shuǐ",
      "ru": "вода",
      "pronunciation": "[шуэй]",
      "example_tr": "喝水",
      "example_ru": "пить воду"
    },
    {
      "tr": "火 huǒ",
      "ru": "огонь",
      "pronunciation": "[хуо]",
      "example_tr": "大火",
      "example_ru": "большой огонь"
    },
    {
      "tr": "上 shàng",
      "ru": "вверх",
      "pronunciation": "[шан]",
      "example_tr": "上面",
      "example_ru": "сверху"
    },
    {
      "tr": "下 xià",
      "ru": "вниз",
      "pronunciation": "[ся]",
      "example_tr": "下面",
      "example_ru": "снизу"
    }
  ],
  "dialogue": {
    "title": "Диалог урока 11",
    "context": "Практика произношения и чтения.",
    "lines": [
      {
        "speaker": "老师",
        "tr": "一个",
        "ru": "один",
        "note": "Слушай и повторяй тон"
      },
      {
        "speaker": "学生",
        "tr": "二月",
        "ru": "февраль",
        "note": "Произноси с правильным тоном"
      },
      {
        "speaker": "老师",
        "tr": "三点",
        "ru": "три часа",
        "note": "Обрати внимание на тон"
      }
    ]
  },
  "cultural_note": {
    "title": "Китайская письменность",
    "text": "Китайская письменность — древнейшая непрерывно используемая система письма в мире. Первые иероглифы найдены на гадательных костях (甲骨文) около 1200 г. до н.э. В 1950-х годах в КНР провели упрощение: многие иероглифы стали писаться проще. Тайвань и Гонконг используют традиционные сложные иероглифы."
  },
  "exercises": [
    {
      "id": "ex_1",
      "type": "multiple_choice",
      "question": "Сколько тонов в китайском языке?",
      "options": [
        "3",
        "4",
        "5",
        "6"
      ],
      "correctAnswer": "4",
      "explanation": "В китайском 4 основных тона + нейтральный. Тон — часть слова: ma с разными тонами = мама/конопля/лошадь/ругать."
    },
    {
      "id": "ex_2",
      "type": "multiple_choice",
      "question": "Что такое пиньинь?",
      "options": [
        "Китайский алфавит",
        "Латинская запись китайских звуков",
        "Иероглифическое письмо",
        "Система счёта"
      ],
      "correctAnswer": "Латинская запись китайских звуков",
      "explanation": "Пиньинь (拼音 pīnyīn) — система латинской транскрипции. Используется для обучения произношению. Не является алфавитом в полном смысле."
    },
    {
      "id": "ex_3",
      "type": "multiple_choice",
      "question": "1-й тон в пиньине обозначается:",
      "options": [
        "á",
        "ǎ",
        "à",
        "ā"
      ],
      "correctAnswer": "ā",
      "explanation": "ā = 1-й тон (горизонтальная черта = ровный звук). á = 2-й (восходящий). ǎ = 3-й (падающий-восходящий). à = 4-й (падающий)."
    },
    {
      "id": "ex_4",
      "type": "match_pairs",
      "question": "Соедини тоны с описанием",
      "pairs": [
        {
          "left": "ā (1-й)",
          "right": "Ровный высокий"
        },
        {
          "left": "á (2-й)",
          "right": "Восходящий"
        },
        {
          "left": "ǎ (3-й)",
          "right": "Падающий-восходящий"
        },
        {
          "left": "à (4-й)",
          "right": "Резко падающий"
        }
      ],
      "correctAnswer": "all",
      "explanation": "1-й=ровный, 2-й=восходящий↗, 3-й=вниз-вверх↘↗, 4-й=падающий↘. Запомни через движение руки!"
    },
    {
      "id": "ex_5",
      "type": "multiple_choice",
      "question": "Буква x в пиньине произносится как:",
      "options": [
        "[кс]",
        "[з]",
        "между [с] и [ш]",
        "[ш]"
      ],
      "correctAnswer": "между [с] и [ш]",
      "explanation": "x в пиньине = звук между [с] и [ш], похожий на немецкий 'ich'. НЕ как английский [кс]! Пример: 学习 xuéxí = учёба."
    },
    {
      "id": "ex_6",
      "type": "multiple_choice",
      "question": "Что такое радикал (部首)?",
      "options": [
        "Произношение иероглифа",
        "Смысловой ключ-компонент иероглифа",
        "Порядок черт",
        "Тон слова"
      ],
      "correctAnswer": "Смысловой ключ-компонент иероглифа",
      "explanation": "部首 bùshǒu = радикал. 女 (женщина) входит в 妈 (мама), 姐 (сестра), 好 (хорошо). Радикал подсказывает смысловое поле."
    },
    {
      "id": "ex_7",
      "type": "fill_blank",
      "question": "Иероглиф 明 (яркий) состоит из:",
      "options": [
        "日+日",
        "日+月",
        "口+日",
        "月+月"
      ],
      "correctAnswer": "日+月",
      "explanation": "明 (míng = яркий/луна) = 日 (солнце) + 月 (луна). Солнце+луна = яркий! Это логика составных иероглифов."
    },
    {
      "id": "ex_8",
      "type": "multiple_choice",
      "question": "В каком порядке пишутся черты иероглифа?",
      "options": [
        "Справа налево и снизу вверх",
        "Слева направо и сверху вниз",
        "В любом порядке",
        "Снизу вверх"
      ],
      "correctAnswer": "Слева направо и сверху вниз",
      "explanation": "Правила порядка черт: сверху вниз (先上后下), слева направо (先左后右), снаружи внутрь (先外后内). Это важно для правильного написания!"
    }
  ],
  "summary": {
    "title": "Итог урока",
    "points": [
      "Писать первые 10 иероглифов",
      "Запомнить порядок черт",
      "Понять пиктографический смысл",
      "Читать их в пиньине"
    ],
    "next_lesson": "Урок 12"
  }
}