{
  "id": "lesson_20",
  "title": "HSK 1 复习 — Итоговое повторение",
  "level": "hsk1",
  "language": "chinese",
  "xpReward": 150,
  "estimatedMinutes": 25,
  "intro": {
    "text": "Урок 20: HSK 1 复习 — Итоговое повторение",
    "goals": [
      "Освоить ключевую лексику",
      "Применить в диалоге",
      "Закрепить упражнениями"
    ]
  },
  "grammar": [
    {
      "id": "g1",
      "title": "Ключевая грамматика",
      "explanation": "Изучи примеры ниже.",
      "table": {
        "headers": [
          "Китайский",
          "Пиньинь",
          "Русский"
        ],
        "rows": [
          [
            "—",
            "—",
            "—"
          ]
        ]
      },
      "note": ""
    }
  ],
  "vocabulary": [
    {
      "tr": "你好 nǐ hǎo",
      "ru": "Привет",
      "pronunciation": "ни-хао",
      "example_tr": "你好！很高兴认识你！",
      "example_ru": "Привет! Очень рада познакомиться!"
    },
    {
      "tr": "我叫...",
      "ru": "Меня зовут...",
      "pronunciation": "во-цзяо",
      "example_tr": "我叫安娜，我是哈萨克斯坦人。",
      "example_ru": "Меня зовут Анна, я из Казахстана."
    },
    {
      "tr": "一二三四五六七八九十",
      "ru": "числа 1-10",
      "pronunciation": "—",
      "example_tr": "你有几个？",
      "example_ru": "Сколько у тебя?"
    },
    {
      "tr": "多少钱？",
      "ru": "Сколько стоит?",
      "pronunciation": "дуо-шао-цянь",
      "example_tr": "这个多少钱？",
      "example_ru": "Сколько стоит это?"
    },
    {
      "tr": "在哪里？",
      "ru": "Где находится?",
      "pronunciation": "цзай-на-ли",
      "example_tr": "厕所在哪里？",
      "example_ru": "Где туалет?"
    },
    {
      "tr": "我喜欢...",
      "ru": "Мне нравится...",
      "pronunciation": "во-си-хуань",
      "example_tr": "我喜欢中文！",
      "example_ru": "Мне нравится китайский!"
    },
    {
      "tr": "你好吗？",
      "ru": "Как ты?",
      "pronunciation": "ни-хао-ма",
      "example_tr": "你好吗？—我很好！",
      "example_ru": "Как ты? — Я хорошо!"
    },
    {
      "tr": "谢谢/不客气",
      "ru": "Спасибо/Не за что",
      "pronunciation": "—",
      "example_tr": "谢谢！—不客气。",
      "example_ru": "Спасибо! — Не за что."
    },
    {
      "tr": "对不起/没关系",
      "ru": "Извини/Ничего",
      "pronunciation": "—",
      "example_tr": "对不起！—没关系。",
      "example_ru": "Извини! — Ничего страшного."
    },
    {
      "tr": "我会说一点中文",
      "ru": "Я немного говорю по-китайски",
      "pronunciation": "—",
      "example_tr": "我会说一点中文，请多指教！",
      "example_ru": "Я немного говорю по-китайски, прошу вашего наставления!"
    },
    {
      "tr": "再见",
      "ru": "До свидания",
      "pronunciation": "цзай-цзянь",
      "example_tr": "再见！明天见！",
      "example_ru": "До свидания! Увидимся завтра!"
    },
    {
      "tr": "加油！",
      "ru": "Давай! / Не сдавайся!",
      "pronunciation": "цзя-ю",
      "example_tr": "学中文加油！",
      "example_ru": "Давай, учи китайский!"
    }
  ],
  "dialogue": {
    "title": "Диалог урока 20",
    "context": "Практика в реальной ситуации.",
    "lines": [
      {
        "speaker": "А",
        "tr": "你好！很高兴认识你！",
        "ru": "Привет! Очень рада познакомиться!",
        "note": ""
      },
      {
        "speaker": "Б",
        "tr": "我叫安娜，我是哈萨克斯坦人。",
        "ru": "Меня зовут Анна, я из Казахстана.",
        "note": ""
      },
      {
        "speaker": "А",
        "tr": "你有几个？",
        "ru": "Сколько у тебя?",
        "note": ""
      }
    ]
  },
  "cultural_note": {
    "title": "Китайская культура",
    "text": "Китай — великая цивилизация с историей 5000 лет."
  },
  "exercises": [
    {
      "id": "ex_1",
      "type": "multiple_choice",
      "question": "'Как сказать Спасибо?'",
      "options": [
        "对不起",
        "再见",
        "谢谢",
        "没关系"
      ],
      "correctAnswer": "谢谢",
      "explanation": "谢谢 xièxie = Спасибо. Ответ: 不客气 (bú kèqi) = Не за что. Базовая пара вежливости!"
    },
    {
      "id": "ex_2",
      "type": "multiple_choice",
      "question": "Как будет 'Сколько стоит?'",
      "options": [
        "多少人？",
        "多少时间？",
        "多少钱？",
        "多少？"
      ],
      "correctAnswer": "多少钱？",
      "explanation": "多少钱？duōshao qián = Сколько стоит? Самый важный вопрос для шопинга!"
    },
    {
      "id": "ex_3",
      "type": "match_pairs",
      "question": "Итог HSK1: соедини",
      "pairs": [
        {
          "left": "你好",
          "right": "Привет"
        },
        {
          "left": "再见",
          "right": "До свидания"
        },
        {
          "left": "谢谢",
          "right": "Спасибо"
        },
        {
          "left": "对不起",
          "right": "Извините"
        }
      ],
      "correctAnswer": "all",
      "explanation": "你好=привет, 再见=до свидания, 谢谢=спасибо, 对不起=извините. Базовый набор!"
    },
    {
      "id": "ex_4",
      "type": "multiple_choice",
      "question": "'Как ты?' по-китайски:",
      "options": [
        "你是谁？",
        "你好吗？",
        "你在哪里？",
        "你叫什么？"
      ],
      "correctAnswer": "你好吗？",
      "explanation": "你好吗？= Как ты? 你好！— это приветствие. 吗 превращает в вопрос."
    },
    {
      "id": "ex_5",
      "type": "fill_blank",
      "question": "«我会说一点___» = «Я немного говорю по-китайски»",
      "options": [
        "英语",
        "法语",
        "中文",
        "日语"
      ],
      "correctAnswer": "中文",
      "explanation": "中文 zhōngwén = китайский язык (разговорное). 汉语 = официальное название. Оба правильны."
    },
    {
      "id": "ex_6",
      "type": "multiple_choice",
      "question": "'Мне нравится китайский язык' по-китайски:",
      "options": [
        "我学中文。",
        "我喜欢中文！",
        "我会中文。",
        "我要中文。"
      ],
      "correctAnswer": "我喜欢中文！",
      "explanation": "喜欢 xǐhuan = нравиться/любить. 中文 = китайский язык. 我喜欢中文！= Мне нравится китайский!"
    },
    {
      "id": "ex_7",
      "type": "multiple_choice",
      "question": "加油！означает:",
      "options": [
        "пить масло",
        "прибавить масла",
        "давай / не сдавайся",
        "заправить машину"
      ],
      "correctAnswer": "давай / не сдавайся",
      "explanation": "加油！jiāyóu = Давай! Не сдавайся! Буквально: «добавь масла/топлива». Универсальный возглас поддержки."
    },
    {
      "id": "ex_8",
      "type": "fill_blank",
      "question": "«___！明天见！» = «До свидания! Увидимся завтра!»",
      "options": [
        "你好",
        "谢谢",
        "再见",
        "对不起"
      ],
      "correctAnswer": "再见",
      "explanation": "再见 zàijiàn = до свидания. 明天见 = до завтра (увидимся завтра). 见 = видеться."
    }
  ],
  "summary": {
    "title": "Что ты выучил",
    "points": [
      "HSK 1 复习 — Итоговое повторение"
    ],
    "next_lesson": "Поздравляем! HSK 1 завершён!"
  }
}