{
  "id": "lesson_20",
  "title": "A0 Tekrar — Итог нулевого уровня",
  "level": "a0",
  "language": "turkish",
  "xpReward": 40,
  "estimatedMinutes": 20,
  "intro": {
    "text": "Поздравляем! Ты освоил основы турецкой фонетики и алфавита. Теперь ты можешь читать любое турецкое слово, произносить специфические звуки, понимаешь гармонию гласных. Ты готов к A1!",
    "goals": [
      "Повторить весь алфавит",
      "Прочитать связный текст",
      "Применить гармонию гласных",
      "Оценить готовность к A1"
    ]
  },
  "grammar": [
    {
      "id": "g1",
      "title": "Ключевая тема: Итог нулевого уровня",
      "explanation": "Поздравляем! Ты освоил основы турецкой фонетики и алфавита. Теперь ты можешь читать любое турецкое слово, произносить специфические звуки, понимаешь гармонию гласных. Ты готов к A1!",
      "table": {
        "headers": [
          "Буква/Правило",
          "Произношение",
          "Пример"
        ],
        "rows": [
          [
            "Tebrikler!",
            "Поздравляем!",
            "тэб-рик-лэр"
          ],
          [
            "Alfabe",
            "алфавит",
            "аль-фа-бэ"
          ],
          [
            "Ünlü uyumu",
            "гармония гласных",
            "юн-лю у-йу-му"
          ],
          [
            "Ses bilgisi",
            "фонетика",
            "сэс биль-ги-си"
          ],
          [
            "Sesleri",
            "звуки",
            "сэс-лэ-ри"
          ]
        ]
      },
      "note": "💡 Повторить весь алфавит"
    }
  ],
  "vocabulary": [
    {
      "tr": "Tebrikler!",
      "ru": "Поздравляем!",
      "pronunciation": "тэб-рик-лэр",
      "example_tr": "A0'ı bitirdin!",
      "example_ru": "Ты завершил A0!"
    },
    {
      "tr": "Alfabe",
      "ru": "алфавит",
      "pronunciation": "аль-фа-бэ",
      "example_tr": "Türk alfabesi.",
      "example_ru": "Турецкий алфавит."
    },
    {
      "tr": "Ünlü uyumu",
      "ru": "гармония гласных",
      "pronunciation": "юн-лю у-йу-му",
      "example_tr": "Çok önemli kural.",
      "example_ru": "Очень важное правило."
    },
    {
      "tr": "Ses bilgisi",
      "ru": "фонетика",
      "pronunciation": "сэс биль-ги-си",
      "example_tr": "Ses bilgisi önemli.",
      "example_ru": "Фонетика важна."
    },
    {
      "tr": "Sesleri",
      "ru": "звуки",
      "pronunciation": "сэс-лэ-ри",
      "example_tr": "Tüm sesleri biliyorum.",
      "example_ru": "Знаю все звуки."
    },
    {
      "tr": "Okuma",
      "ru": "чтение",
      "pronunciation": "о-ку-ма",
      "example_tr": "Türkçe okuyorum.",
      "example_ru": "Читаю по-турецки."
    },
    {
      "tr": "Yazma",
      "ru": "письмо",
      "pronunciation": "йаз-ма",
      "example_tr": "Türkçe yazıyorum.",
      "example_ru": "Пишу по-турецки."
    },
    {
      "tr": "Dinleme",
      "ru": "слушание",
      "pronunciation": "дин-лэ-мэ",
      "example_tr": "Türkçe dinliyorum.",
      "example_ru": "Слушаю турецкий."
    },
    {
      "tr": "A1'e hazırım",
      "ru": "Готов к A1",
      "pronunciation": "а бир-э ха-зы-рым",
      "example_tr": "A1'e geçiyorum!",
      "example_ru": "Перехожу на A1!"
    },
    {
      "tr": "Öğreniyorum",
      "ru": "я учусь",
      "pronunciation": "ою-рэ-ни-йо-рум",
      "example_tr": "Türkçe öğreniyorum.",
      "example_ru": "Учу турецкий."
    },
    {
      "tr": "Devam",
      "ru": "продолжение",
      "pronunciation": "дэ-вам",
      "example_tr": "Devam edelim!",
      "example_ru": "Продолжим!"
    },
    {
      "tr": "Başarı",
      "ru": "успех",
      "pronunciation": "ба-ша-ры",
      "example_tr": "Başarılar!",
      "example_ru": "Удачи!"
    }
  ],
  "dialogue": {
    "title": "Практика урока 20",
    "context": "Изучаем звуки и буквы.",
    "lines": [
      {
        "speaker": "Öğretmen",
        "tr": "A0'ı bitirdin!",
        "ru": "Ты завершил A0!",
        "note": "Слушай и повторяй"
      },
      {
        "speaker": "Öğrenci",
        "tr": "Türk alfabesi.",
        "ru": "Турецкий алфавит.",
        "note": "Произноси чётко"
      },
      {
        "speaker": "Öğretmen",
        "tr": "Çok önemli kural.",
        "ru": "Очень важное правило.",
        "note": "Ещё раз"
      }
    ]
  },
  "cultural_note": {
    "title": "Турецкий язык",
    "text": "Турецкий — тюркский язык с 80+ миллионами носителей. Он агглютинативный: значения добавляются суффиксами. Это делает его логичным и системным. Алфавит введён Ататюрком в 1928 году — до этого использовалась арабская вязь."
  },
  "exercises": [
    {
      "id": "ex_1",
      "type": "multiple_choice",
      "question": "Урок 20: какое правило самое важное?",
      "options": [
        "Повторить весь алфавит",
        "Запомнить все слова",
        "Много говорить",
        "Слушать музыку"
      ],
      "correctAnswer": "Повторить весь алфавит",
      "explanation": "Главная цель урока 20: Повторить весь алфавит"
    },
    {
      "id": "ex_2",
      "type": "multiple_choice",
      "question": "Турецкий алфавит состоит из скольких букв?",
      "options": [
        "26",
        "28",
        "29",
        "32"
      ],
      "correctAnswer": "29",
      "explanation": "В турецком алфавите 29 букв. Нет x, w, q. Есть ç, ğ, ı, ö, ş, ü."
    },
    {
      "id": "ex_3",
      "type": "multiple_choice",
      "question": "Как читается буква C в турецком?",
      "options": [
        "[ц]",
        "[к]",
        "[дж]",
        "[с]"
      ],
      "correctAnswer": "[дж]",
      "explanation": "C в турецком всегда [дж]: cam = [джам] (стекло). Никогда не [ц] как в русском!"
    },
    {
      "id": "ex_4",
      "type": "multiple_choice",
      "question": "Что такое гармония гласных?",
      "options": [
        "Красивое пение",
        "Суффикс берёт гласную той же группы что корень",
        "Удвоение гласных",
        "Перестановка букв"
      ],
      "correctAnswer": "Суффикс берёт гласную той же группы что корень",
      "explanation": "Ünlü uyumu = гармония гласных. Задние (a,ı,o,u) → суффикс с a/ı. Передние (e,i,ö,ü) → суффикс с e/i."
    },
    {
      "id": "ex_5",
      "type": "multiple_choice",
      "question": "Буква Ğ (юмушак ге) произносится как:",
      "options": [
        "[г]",
        "[й]",
        "удлиняет предыдущую гласную",
        "[х]"
      ],
      "correctAnswer": "удлиняет предыдущую гласную",
      "explanation": "Ğ = немая буква. dağ = [да-а] (гора). Она удлиняет гласную, сама не произносится."
    },
    {
      "id": "ex_6",
      "type": "fill_blank",
      "question": "Турецкое слово 'çay' читается как:",
      "options": [
        "[цай]",
        "[чай]",
        "[кай]",
        "[джай]"
      ],
      "correctAnswer": "[чай]",
      "explanation": "ç = [ч]. çay = [чай] = чай. Это одно из первых слов — оно пишется почти как по-русски!"
    },
    {
      "id": "ex_7",
      "type": "multiple_choice",
      "question": "В каком порядке строится турецкое предложение?",
      "options": [
        "Подлежащее-Сказуемое-Дополнение",
        "Дополнение-Подлежащее-Сказуемое",
        "Подлежащее-Дополнение-Сказуемое",
        "Сказуемое-Подлежащее-Дополнение"
      ],
      "correctAnswer": "Подлежащее-Дополнение-Сказуемое",
      "explanation": "SOV = Subject-Object-Verb. Глагол ВСЕГДА в конце. Ben kitap okuyorum = Я книгу читаю."
    },
    {
      "id": "ex_8",
      "type": "match_pairs",
      "question": "Соедини буквы с произношением",
      "pairs": [
        {
          "left": "ç",
          "right": "[ч]"
        },
        {
          "left": "ş",
          "right": "[ш]"
        },
        {
          "left": "c",
          "right": "[дж]"
        },
        {
          "left": "y",
          "right": "[й]"
        }
      ],
      "correctAnswer": "all",
      "explanation": "ç=[ч], ş=[ш], c=[дж], y=[й]. Самые важные специфические согласные турецкого."
    }
  ],
  "summary": {
    "title": "Итог урока",
    "points": [
      "Повторить весь алфавит",
      "Прочитать связный текст",
      "Применить гармонию гласных",
      "Оценить готовность к A1"
    ],
    "next_lesson": "Переходим к A1!"
  }
}